electron/__init__.py
electron/electron.py
electron/hello.py
electron-0.0.3.dist-info/METADATA
electron-0.0.3.dist-info/WHEEL
electron-0.0.3.dist-info/top_level.txt
electron-0.0.3.dist-info/RECORD
