Metadata-Version: 2.1
Name: electron
Version: 0.0.3
Summary: A web framework for Python
Home-page: https://pornhub.com
Author: CrowXeo
Author-email: crowxeo@gmail.com
Classifier: Programming Language :: Python :: 3.11
Classifier: License :: OSI Approved :: MIT License
Classifier: Operating System :: OS Independent
Requires-Python: >=3.11
